pycmx/__init__.py
pycmx/cdl.py
pycmx/channel_map.py
pycmx/edit.py
pycmx/edit_list.py
pycmx/event.py
pycmx/parse_cmx_events.py
pycmx/parse_cmx_statements.py
pycmx/statements.py
pycmx/transition.py
pycmx/util.py
pycmx-1.4.0.dist-info/METADATA
pycmx-1.4.0.dist-info/WHEEL
pycmx-1.4.0.dist-info/licenses/LICENSE
pycmx-1.4.0.dist-info/RECORD
