Metadata-Version: 2.4
Name: pycmx
Version: 1.4.0
Summary: Python CMX 3600 Edit Decision List Parser
License: MIT
License-File: LICENSE
Keywords: parser,film,broadcast
Author: Jamie Hardt
Author-email: jamiehardt@me.com
Requires-Python: >=3.8,<4.0
Classifier: Development Status :: 5 - Production/Stable
Classifier: License :: OSI Approved :: MIT License
Classifier: Programming Language :: Python :: 3
Classifier: Programming Language :: Python :: 3.8
Classifier: Programming Language :: Python :: 3.9
Classifier: Programming Language :: Python :: 3.10
Classifier: Programming Language :: Python :: 3.11
Classifier: Programming Language :: Python :: 3.12
Classifier: Programming Language :: Python :: 3.13
Classifier: Programming Language :: Python :: 3.14
Classifier: Topic :: Multimedia
Classifier: Topic :: Multimedia :: Video
Classifier: Topic :: Text Processing
Provides-Extra: doc
Requires-Dist: sphinx (>=5.3.0) ; extra == "doc"
Requires-Dist: sphinx_rtd_theme (>=1.1.1) ; extra == "doc"
Project-URL: Documentation, https://pycmx.readthedocs.io/
Project-URL: Homepage, https://github.com/iluvcapra/pycmx
Project-URL: Repository, https://github.com/iluvcapra/pycmx.git
Project-URL: Tracker, https://github.com/iluvcapra/pycmx/issues
